{"BaseModel.b896b6a8-8c12-4488-883c-c56919a3fc52": {"id": "b896b6a8-8c12-4488-883c-c56919a3fc52", "created_at": "2024-03-11T05:31:38.990680", "updated_at": "2024-03-12T17:08:31.517004", "my_number": 89, "email": "aibnb@mail.com", "__class__": "BaseModel"}, "User.84c51edc-8be3-40e5-aebb-d0c2c0ea0704": {"id": "84c51edc-8be3-40e5-aebb-d0c2c0ea0704", "created_at": "2024-03-12T17:41:02.788036", "updated_at": "2024-03-12T17:41:02.788046", "first_name": "Betty", "last_name": "Bar", "email": "airbnb@mail.com", "password": "root", "__class__": "BaseModel"}, "User.851caa7b-de1b-4827-8aac-12cd7b7117b1": {"id": "851caa7b-de1b-4827-8aac-12cd7b7117b1", "created_at": "2024-03-12T17:41:02.788771", "updated_at": "2024-03-12T17:41:02.788782", "first_name": "John", "email": "airbnb2@mail.com", "password": "root", "__class__": "BaseModel"}, "User.31f6bd02-7196-4392-a365-33ecdbf7d148": {"id": "31f6bd02-7196-4392-a365-33ecdbf7d148", "created_at": "2024-03-12T17:41:35.489725", "updated_at": "2024-03-12T17:41:35.489741", "first_name": "Betty", "last_name": "Bar", "email": "airbnb@mail.com", "password": "root", "__class__": "BaseModel"}, "User.4aaf7756-0ac8-4269-947f-07c6d46a9169": {"id": "4aaf7756-0ac8-4269-947f-07c6d46a9169", "created_at": "2024-03-12T17:41:35.492853", "updated_at": "2024-03-12T17:41:35.492898", "first_name": "John", "email": "airbnb2@mail.com", "password": "root", "__class__": "BaseModel"}, "User.285dee61-42ec-4e72-bfff-fe5ba1036fef": {"id": "285dee61-42ec-4e72-bfff-fe5ba1036fef", "created_at": "2024-03-12T17:41:43.260451", "updated_at": "2024-03-12T17:41:43.260471", "first_name": "Betty", "last_name": "Bar", "email": "airbnb@mail.com", "password": "root", "__class__": "BaseModel"}, "User.fa81ef80-17ce-4b84-8676-2d0cb3ffdb8c": {"id": "fa81ef80-17ce-4b84-8676-2d0cb3ffdb8c", "created_at": "2024-03-12T17:41:43.262655", "updated_at": "2024-03-12T17:41:43.262671", "first_name": "John", "email": "airbnb2@mail.com", "password": "root", "__class__": "BaseModel"}, "BaseModel.7dee82a8-50f4-4ab1-9474-ec84bdd01097": {"id": "7dee82a8-50f4-4ab1-9474-ec84bdd01097", "created_at": "2024-03-12T17:45:03.004404", "updated_at": "2024-03-12T17:45:03.004426", "__class__": "BaseModel"}, "BaseModel.2b04f169-5aa8-4e12-a481-07b90b9b678f": {"id": "2b04f169-5aa8-4e12-a481-07b90b9b678f", "created_at": "2024-03-12T17:48:15.280457", "updated_at": "2024-03-12T17:48:15.280477", "__class__": "BaseModel"}, "User.e177e557-da0d-469c-8a25-b92ea7b9f54c": {"id": "e177e557-da0d-469c-8a25-b92ea7b9f54c", "created_at": "2024-03-12T17:48:45.562276", "updated_at": "2024-03-12T17:48:45.562289", "first_name": "Betty", "last_name": "Bar", "email": "airbnb@mail.com", "password": "root", "__class__": "BaseModel"}, "User.0980050e-48b7-4f63-bfb5-e00d193df0f1": {"id": "0980050e-48b7-4f63-bfb5-e00d193df0f1", "created_at": "2024-03-12T17:48:45.563417", "updated_at": "2024-03-12T17:48:45.563445", "first_name": "John", "email": "airbnb2@mail.com", "password": "root", "__class__": "BaseModel"}, "User.834aa04d-1a54-422f-8eb0-933e8773e3cb": {"id": "834aa04d-1a54-422f-8eb0-933e8773e3cb", "created_at": "2024-03-12T17:48:57.127431", "updated_at": "2024-03-12T17:48:57.127463", "first_name": "Betty", "last_name": "Bar", "email": "airbnb@mail.com", "password": "root", "__class__": "User"}, "BaseModel.5ee622da-6ffc-43e6-97fc-4f64dec95b84": {"id": "5ee622da-6ffc-43e6-97fc-4f64dec95b84", "created_at": "2024-03-12T21:35:28.834874", "updated_at": "2024-03-12T21:35:28.834906", "__class__": "BaseModel"}, "User.ae4c9ce7-0465-46ae-a0fc-e1d489f78222": {"id": "ae4c9ce7-0465-46ae-a0fc-e1d489f78222", "created_at": "2024-03-12T21:39:51.711383", "updated_at": "2024-03-12T21:40:45.677321", "__class__": "User"}, "BaseModel.a47a267b-9b9d-4c84-ac4c-2c24b68715c2": {"id": "a47a267b-9b9d-4c84-ac4c-2c24b68715c2", "created_at": "2024-03-12T22:35:24.302205", "updated_at": "2024-03-12T22:35:24.302225", "__class__": "BaseModel"}}